{
  "schema_version": 1,
  "channels": {
    "stable": {
      "version": "1.4.82",
      "published_at": "2026-04-24T02:36:05Z",
      "changelog": "Exclude already-associated image content during private image resolution to avoid linking stale cached images",
      "assets": {
        "exe": {
          "kind": "exe",
          "download_url": "https://github.com/harrywang1024/CloudAppRobot-Releases/releases/download/v1.4.82/CloudAppRobot.exe",
          "sha256": "c18ec2b401a659a6176b5cd5369f419356c8f2a00d9035a4c11f62526c3bfa54",
          "size": 36245410
        },
        "py": {
          "download_url": "",
          "sha256": "",
          "size": null
        },
        "bundle": {
          "kind": "bundle_zip",
          "download_url": "https://github.com/harrywang1024/CloudAppRobot-Releases/releases/download/v1.4.82/CloudAppRobot-bundle.zip",
          "sha256": "f06bf1a835accb3d3866df7486e6691b014ef9b78cda4bf483ddccb1bb25e676",
          "size": 205049452
        }
      }
    }
  }
}
